bibo/__init__.py
bibo/bibo.py
bibo/cite.py
bibo/internals.py
bibo/models.py
bibo/query.py
click_constraints/__init__.py
click_constraints/click_constraints.py
pybibs/__init__.py
pybibs/_internals.py
pybibs/pybibs.py
bibo-0.1.9.dist-info/LICENSE
bibo-0.1.9.dist-info/METADATA
bibo-0.1.9.dist-info/WHEEL
bibo-0.1.9.dist-info/entry_points.txt
bibo-0.1.9.dist-info/top_level.txt
bibo-0.1.9.dist-info/RECORD
